cleaner_id/__init__.py
cleaner_id/slang_list.py
cleaner_id-0.1.3.dist-info/LICENSE
cleaner_id-0.1.3.dist-info/METADATA
cleaner_id-0.1.3.dist-info/WHEEL
cleaner_id-0.1.3.dist-info/top_level.txt
cleaner_id-0.1.3.dist-info/RECORD
