Metadata-Version: 2.1
Name: cleaner-id
Version: 0.1.3
Summary: Text Preprocessing berbahasa indonesia
Home-page: https://github.com/pypa/sampleproject
Author: Tarangga Arief
Author-email: tarangga.arief@gmail.com
Project-URL: Bug Tracker, https://github.com/pypa/sampleproject/issues
Classifier: Programming Language :: Python :: 3
Classifier: License :: OSI Approved :: MIT License
Classifier: Operating System :: OS Independent
Requires-Python: >=3.6
License-File: LICENSE
